README.md
pyproject.toml
setup.py
yellyproxies/__init__.py
yellyproxies.egg-info/PKG-INFO
yellyproxies.egg-info/SOURCES.txt
yellyproxies.egg-info/dependency_links.txt
yellyproxies.egg-info/top_level.txt